{
  "toc": {
    "sections": [
      {
        "title": "Features",
        "source": "README.md",
        "expand": true,
        "url": "index.html",
        "slug": "index",
        "headings": [
          {
            "title": "Features",
            "depth": 3,
            "id": "features"
          },
          {
            "title": "Download",
            "depth": 3,
            "id": "download"
          },
          {
            "title": "How to use it",
            "depth": 3,
            "id": "how-to-use-it"
          },
          {
            "title": "Android",
            "depth": 3,
            "id": "android"
          },
          {
            "title": "Who made this",
            "depth": 2,
            "id": "who-made-this"
          },
          {
            "title": "Contribute",
            "depth": 2,
            "id": "contribute"
          },
          {
            "title": "Bugs and Feedback",
            "depth": 2,
            "id": "bugs-and-feedback"
          },
          {
            "title": "License",
            "depth": 2,
            "id": "license"
          }
        ]
      }
    ]
  },
  "index": {
    "index.html": {
      "source": "README.md",
      "title": "Features",
      "pageTitle": "Features",
      "slug": "index",
      "headings": [
        {
          "title": "Features",
          "depth": 3,
          "id": "features"
        },
        {
          "title": "Download",
          "depth": 3,
          "id": "download"
        },
        {
          "title": "How to use it",
          "depth": 3,
          "id": "how-to-use-it"
        },
        {
          "title": "Android",
          "depth": 3,
          "id": "android"
        },
        {
          "title": "Who made this",
          "depth": 2,
          "id": "who-made-this"
        },
        {
          "title": "Contribute",
          "depth": 2,
          "id": "contribute"
        },
        {
          "title": "Bugs and Feedback",
          "depth": 2,
          "id": "bugs-and-feedback"
        },
        {
          "title": "License",
          "depth": 2,
          "id": "license"
        }
      ]
    }
  },
  "sources": {
    "README.md": "index.html"
  }
}
